pd_explain/__init__.py
pd_explain/core/__init__.py
pd_explain/core/explainable_data_frame.py
pd_explain/core/explainable_group_by_dataframe.py
pd_explain/core/explainable_group_by_series.py
pd_explain/core/explainable_series.py
pd_explain/experimental/__init__.py
pd_explain/experimental/experimental_llm_integrations/__init__.py
pd_explain/experimental/experimental_llm_integrations/llm_query_recommender.py
pd_explain/experimental/experimental_llm_integrations/query_refiner.py
pd_explain/experimental/query_recommenders/__init__.py
pd_explain/experimental/query_recommenders/consts.py
pd_explain/experimental/query_recommenders/llm_based_query_recommender.py
pd_explain/experimental/query_recommenders/query_logger.py
pd_explain/experimental/query_recommenders/query_recommender_interface.py
pd_explain/experimental/query_recommenders/query_score_functions.py
pd_explain/explainers/__init__.py
pd_explain/explainers/explainer_factory.py
pd_explain/explainers/explainer_interface.py
pd_explain/explainers/fedex_explainer.py
pd_explain/explainers/many_to_one_explainer.py
pd_explain/explainers/outlier_explainer.py
pd_explain/explainers/beta_explainers/__init__.py
pd_explain/explainers/beta_explainers/metainsight_explainer.py
pd_explain/llm_integrations/__init__.py
pd_explain/llm_integrations/client.py
pd_explain/llm_integrations/consts.py
pd_explain/llm_integrations/explanation_reasoning.py
pd_explain/llm_integrations/llm_integration_interface.py
pd_explain/llm_integrations/automated_data_exploration/__init__.py
pd_explain/llm_integrations/automated_data_exploration/automated_data_exploration.py
pd_explain/llm_integrations/automated_data_exploration/data_structures.py
pd_explain/llm_integrations/automated_data_exploration/visualizer.py
pd_explain/llm_integrations/beta_integrations/__init__.py
pd_explain/llm_integrations/beta_integrations/visualization_beautifier.py
pd_explain/utils/__init__.py
pd_explain/utils/global_values.py
pd_explain/utils/utils.py
pd_explain-1.1.2.dist-info/licenses/LICENSE
pd_explain-1.1.2.dist-info/licenses/NOTICE
pd_explain-1.1.2.dist-info/METADATA
pd_explain-1.1.2.dist-info/WHEEL
pd_explain-1.1.2.dist-info/top_level.txt
pd_explain-1.1.2.dist-info/RECORD
