Metadata-Version: 2.4
Name: pd_explain
Version: 1.1.2
Summary: Create explanation to dataframe
Project-URL: Git, https://github.com/analysis-bots/pd-explain
License-File: LICENSE
License-File: NOTICE
Requires-Dist: wheel
Requires-Dist: pandas>=2.2.3
Requires-Dist: numpy>=2.1.3
Requires-Dist: python-dotenv
Requires-Dist: singleton-decorator
Requires-Dist: matplotlib>=3.9.0
Requires-Dist: fedex-generator>=1.0.6
Requires-Dist: cluster-explorer>=1.0.2
Requires-Dist: external-explainers>=1.0.0
Requires-Dist: python-dotenv~=1.0.0
Requires-Dist: ipywidgets>=8.1.0
Requires-Dist: ipycytoscape>=1.3.0
Requires-Dist: together>=1.4.6
Requires-Dist: dill>=0.3.8
Requires-Dist: networkx>=3.2
Dynamic: description
Dynamic: description-content-type
Dynamic: license-file
Dynamic: project-url
Dynamic: requires-dist
Dynamic: summary
